Workbook

Sheet Requirement Register
A1: ID | B1: Kapitel | C1: Kapitelrubrik | D1: Sektion | E1: Sektionsrubrik | F1: Normativ term | G1: Kravtext
A2: MI-01-001 | B2: 1 | C2: Mobile Intelligence som systemdomän i Omnira | D2: 1.3 | E2: Mobilappen är inte hela domänen | F2: FÅR INTE | G2: Mobile Intelligence SKA definieras som en systemdomän och FÅR INTE reduceras till Omniras mobilapp.
A3: MI-01-002 | B3: 1 | C3: Mobile Intelligence som systemdomän i Omnira | D3: 1.3 | E3: Mobilappen är inte hela domänen | F3: FÅR INTE | G3: Mobilappen SKA vara en kontroll- och interaktionsyta för domänen, men den FÅR INTE vara enda sanningskälla för workflows, authority, approvals eller projektstatus.
A4: MI-01-003 | B4: 1 | C4: Mobile Intelligence som systemdomän i Omnira | D4: 1.4 | E4: Mobilen som fullvärdig Omnira-node | F4: SKA | G4: Mobilen SKA behandlas som en betrodd eller obetrodd Omnira-node beroende på verifierad device identity och aktiv trust-status.
A5: MI-01-004 | B5: 1 | C5: Mobile Intelligence som systemdomän i Omnira | D5: 1.4 | E5: Mobilen som fullvärdig Omnira-node | F5: SKA | G5: En betrodd mobilnod KAN ha flera roller samtidigt, men varje roll och capability SKA vara explicit definierad.
A6: MI-01-005 | B6: 1 | C6: Mobile Intelligence som systemdomän i Omnira | D6: 1.4 | E6: Mobilen som fullvärdig Omnira-node | F6: FÅR INTE | G6: Att en mobil är betrodd FÅR INTE automatiskt ge den full administration, tillgång till alla credentials eller rätt att exekvera alla workflows.
A7: MI-01-006 | B7: 1 | C7: Mobile Intelligence som systemdomän i Omnira | D7: 1.5 | E7: Atlas roll i mobilarkitekturen | F7: SKA | G7: Atlas SKA vara det centrala koordinations- och beslutsstödet för Mobile Intelligence.
A8: MI-01-007 | B8: 1 | C8: Mobile Intelligence som systemdomän i Omnira | D8: 1.5 | E8: Atlas roll i mobilarkitekturen | F8: FÅR INTE | G8: Atlas FÅR INTE behandlas som en global root-behörighet som kan kringgå scope, authority, project isolation eller credential isolation.
A9: MI-01-008 | B9: 1 | C9: Mobile Intelligence som systemdomän i Omnira | D9: 1.5 | E9: Atlas roll i mobilarkitekturen | F9: FÅR INTE | G9: Atlas SKA kunna rekommendera en handling som ligger utanför nuvarande mandat, men FÅR INTE exekvera den innan nödvändigt godkännande finns.
A10: MI-01-009 | B10: 1 | C10: Mobile Intelligence som systemdomän i Omnira | D10: 1.6 | E10: Projektagenter och externa identiteter | F10: SKA | G10: Extern projektidentitet SKA hållas åtskild från intern exekveringsidentitet.
A11: MI-01-010 | B11: 1 | C11: Mobile Intelligence som systemdomän i Omnira | D11: 1.6 | E11: Projektagenter och externa identiteter | F11: FÅR INTE | G11: En projektagent FÅR INTE få tillgång till andra projekt enbart för att Atlas har en global överblick.
A12: MI-01-011 | B12: 1 | C12: Mobile Intelligence som systemdomän i Omnira | D12: 1.6 | E12: Projektagenter och externa identiteter | F12: FÅR INTE | G12: Information om Omniras interna arkitektur FÅR INTE blandas in i projektkommunikation om det inte uttryckligen ingår i projektets godkända externa koncept.
A13: MI-01-012 | B13: 1 | C13: Mobile Intelligence som systemdomän i Omnira | D13: 1.7 | E13: Control surface och execution surface | F13: SKA | G13: Control surface och execution surface SKA behandlas som separata arkitekturdimensioner.
... A507: MI-05-114 | B507: 5 | C507: Authority-modellen L0–L6 | D507: 5.40 | E507: Authority och irreversibilitet | F507: SKA | G507: Irreversibilitet SKA vara en separat riskdimension i authoritybedömningen.
A508: MI-05-115 | B508: 5 | C508: Authority-modellen L0–L6 | D508: 5.40 | E508: Authority och irreversibilitet | G508: En capability kan ha L5 för normala handlingar men L3 för irreversibla undantag.
A509: MI-05-116 | B509: 5 | C509: Authority-modellen L0–L6 | D509: 5.40 | E509: Authority och irreversibilitet | F509: FÅR INTE | G509: L6 FÅR INTE automatiskt omfatta personligt bindande eller förbjudna handlingar.
A510: MI-05-117 | B510: 5 | C510: Authority-modellen L0–L6 | D510: 5.41 | E510: Authority och incidentrespons | F510: SKA | G510: Emergency authority SKA begränsas till fördefinierade riskreducerande handlingar.
A511: MI-05-118 | B511: 5 | C511: Authority-modellen L0–L6 | D511: 5.41 | E511: Authority och incidentrespons | F511: SKA | G511: Automatisk incidentåtgärd SKA meddelas omedelbart.
A512: MI-05-119 | B512: 5 | C512: Authority-modellen L0–L6 | D512: 5.41 | E512: Authority och incidentrespons | F512: FÅR INTE | G512: Emergency authority FÅR INTE användas för permanent privilege expansion.
A513: MI-05-120 | B513: 5 | C513: Authority-modellen L0–L6 | D513: 5.42 | E513: Authority och nödstopp | F513: SKA | G513: Emergency stop SKA omedelbart sänka authority för berörda scopes.
A514: MI-05-121 | B514: 5 | C514: Authority-modellen L0–L6 | D514: 5.42 | E514: Authority och nödstopp | F514: SKA | G514: Nödstopp SKA bevara konfiguration och data om inte separat radering beslutas.
A515: MI-05-122 | B515: 5 | C515: Authority-modellen L0–L6 | D515: 5.42 | E515: Authority och nödstopp | F515: SKA | G515: Återstart SKA återaktivera authority stegvis, inte implicit allt på en gång.
A516: MI-05-123 | B516: 5 | C516: Authority-modellen L0–L6 | D516: 5.43 | E516: Authority och flera agenter | F516: SKA | G516: Delegerad authority SKA vara mindre än eller lika med uppdragsgivarens effective authority.
A517: MI-05-124 | B517: 5 | C517: Authority-modellen L0–L6 | D517: 5.43 | E517: Authority och flera agenter | F517: FÅR INTE | G517: En agent FÅR INTE vidaredelegera authority om detta inte är explicit tillåtet.
A518: MI-05-125 | B518: 5 | C518: Authority-modellen L0–L6 | D518: 5.43 | E518: Authority och flera agenter | F518: SKA | G518: Agentbyte SKA utlösa ny kontroll av authority och dataåtkomst.
A519: MI-05-126 | B519: 5 | C519: Authority-modellen L0–L6 | D519: 5.44 | E519: Authority i organisationer | F519: SKA | G519: Authority governance SKA kunna separeras mellan flera organisatoriska roller.
A520: MI-05-127 | B520: 5 | C520: Authority-modellen L0–L6 | D520: 5.44 | E520: Authority i organisationer | F520: FÅR INTE | G520: Vanlig administratör FÅR INTE automatiskt ändra högsta authoritypolicy.
... A2969: MI-17-031 | B2969: 17 | C2969: Plats, geofencing och fysisk kontext | D2969: 17.10 | E2969: Privat plats | F2969: FÅR INTE | G2969: Projektagent FÅR INTE få personlig plats enbart för att projektet använder mobilen.
A2970: MI-17-032 | B2970: 17 | C2970: Plats, geofencing och fysisk kontext | D2970: 17.10 | E2970: Privat plats | G2970: Projekt får endast få den minsta härledda signal som behövs, exempelvis “användaren är inte tillgänglig för approval just nu”.
A2971: MI-17-033 | B2971: 17 | C2971: Plats, geofencing och fysisk kontext | D2971: 17.10 | E2971: Privat plats | F2971: FÅR INTE | G2971: Privat plats FÅR INTE automatiskt bli globalt långtidsminne.
A2972: MI-17-034 | B2972: 17 | C2972: Plats, geofencing och fysisk kontext | D2972: 17.11 | E2972: Projektplats | F2972: SKA | G2972: Projektplats SKA ha explicit project identity och owner.
A2973: MI-17-035 | B2973: 17 | C2973: Plats, geofencing och fysisk kontext | D2973: 17.11 | E2973: Projektplats | F2973: FÅR INTE | G2973: Projektplats FÅR INTE automatiskt ge projektet användarens personliga rörelsehistorik.
A2974: MI-17-036 | B2974: 17 | C2974: Plats, geofencing och fysisk kontext | D2974: 17.11 | E2974: Projektplats | F2974: SKA | G2974: När personlig plats jämförs mot projektplats SKA endast nödvändig trigger eller relation exponeras till projektet.
A2975: MI-17-037 | B2975: 17 | C2975: Plats, geofencing och fysisk kontext | D2975: 17.12 | E2975: Känsliga platser | F2975: SKA | G2975: Känsliga platser SKA få förhöjd privacyklass.
A2976: MI-17-038 | B2976: 17 | C2976: Plats, geofencing och fysisk kontext | D2976: 17.12 | E2976: Känsliga platser | F2976: FÅR INTE | G2976: Känslig plats FÅR INTE visas i global briefing när en neutral status räcker.
A2977: MI-17-039 | B2977: 17 | C2977: Plats, geofencing och fysisk kontext | D2977: 17.12 | E2977: Känsliga platser | F2977: FÅR INTE | G2977: Känslig plats FÅR INTE delas med projekt eller provider utan konkret behov och explicit scope.
A2978: MI-17-040 | B2978: 17 | C2978: Plats, geofencing och fysisk kontext | D2978: 17.12 | E2978: Känsliga platser | F2978: SKA | G2978: Atlas SKA kunna maskera platsnamn som “privat ärende” eller “otillgänglig” i sekundära vyer.
A2979: MI-17-041 | B2979: 17 | C2979: Plats, geofencing och fysisk kontext | D2979: 17.13 | E2979: Hemmet | F2979: SKA | G2979: Hemmet SKA representeras genom säker platsidentitet eller geofence där exakt adress inte behöver exponeras.
A2980: MI-17-042 | B2980: 17 | C2980: Plats, geofencing och fysisk kontext | D2980: 17.13 | E2980: Hemmet | F2980: FÅR INTE | G2980: Projektagent FÅR INTE få hemadress eller hemkoordinater utan explicit behov.
A2981: MI-17-043 | B2981: 17 | C2981: Plats, geofencing och fysisk kontext | D2981: 17.13 | E2981: Hemmet | F2981: FÅR | G2981: Hemstatus FÅR uttryckas som boolesk signal, exempelvis at_home, när detta räcker.
A2982: MI-17-044 | B2982: 17 | C2982: Plats, geofencing och fysisk kontext | D2982: 17.13 | E2982: Hemmet | F2982: FÅR INTE | G2982: Hemmet FÅR INTE användas för dold närvaroövervakning.
... A3085: MI-17-147 | B3085: 17 | C3085: Plats, geofencing och fysisk kontext | D3085: 17.43 | E3085: Plats och approvals | F3085: FÅR INTE | G3085: Närhet till arbetsplats FÅR INTE automatiskt godkänna projektworkflow.
A3086: MI-17-148 | B3086: 17 | C3086: Plats, geofencing och fysisk kontext | D3086: 17.43 | E3086: Plats och approvals | G3086: Plats kan användas för att föreslå rätt approval surface eller skjuta upp komplex interaktion.
A3087: MI-17-149 | B3087: 17 | C3087: Plats, geofencing och fysisk kontext | D3087: 17.44 | E3087: Plats och human presence | F3087: FÅR INTE | G3087: Geofence membership FÅR INTE betraktas som human presence.
A3088: MI-17-150 | B3088: 17 | C3088: Plats, geofencing och fysisk kontext | D3088: 17.44 | E3088: Plats och human presence | F3088: FÅR INTE | G3088: Bluetoothnärhet FÅR INTE ensam betraktas som användaridentitet.
A3089: MI-17-151 | B3089: 17 | C3089: Plats, geofencing och fysisk kontext | D3089: 17.44 | E3089: Plats och human presence | F3089: SKA | G3089: Human-only action SKA fortsatt kräva den närvaronivå som Kapitel 14 definierar.
A3090: MI-17-152 | B3090: 17 | C3090: Plats, geofencing och fysisk kontext | D3090: 17.45 | E3090: Plats och kalender | F3090: SKA | G3090: Kalenderplats SKA behandlas som planerad destination, inte faktisk position.
A3091: MI-17-153 | B3091: 17 | C3091: Plats, geofencing och fysisk kontext | D3091: 17.45 | E3091: Plats och kalender | F3091: FÅR INTE | G3091: Projektagent FÅR INTE få privata kalenderplatser när endast availability behövs.
A3092: MI-17-154 | B3092: 17 | C3092: Plats, geofencing och fysisk kontext | D3092: 17.45 | E3092: Plats och kalender | F3092: SKA | G3092: Känslig kalenderplats SKA privacyminimeras i briefing och notifieringar.
A3093: MI-17-155 | B3093: 17 | C3093: Plats, geofencing och fysisk kontext | D3093: 17.46 | E3093: Plats och filer | F3093: SKA | G3093: EXIF, dokumentmetadata och filnamn SKA kunna identifieras som platskällor.
A3094: MI-17-156 | B3094: 17 | C3094: Plats, geofencing och fysisk kontext | D3094: 17.46 | E3094: Plats och filer | F3094: FÅR INTE | G3094: Platsmetadata FÅR INTE automatiskt importeras till projekt eller minne.
A3095: MI-17-157 | B3095: 17 | C3095: Plats, geofencing och fysisk kontext | D3095: 17.46 | E3095: Plats och filer | F3095: SKA | G3095: Extern mediaexport SKA kunna ta bort onödig platsmetadata.
A3096: MI-17-158 | B3096: 17 | C3096: Plats, geofencing och fysisk kontext | D3096: 17.47 | E3096: Plats och kommunikation | F3096: SKA | G3096: Plats i kommunikation SKA behandlas enligt kanalens privacyklass.
A3097: MI-17-159 | B3097: 17 | C3097: Plats, geofencing och fysisk kontext | D3097: 17.47 | E3097: Plats och kommunikation | F3097: FÅR INTE | G3097: Live-location-länk FÅR INTE öppnas, följas eller delas vidare utan explicit scope.
A3098: MI-17-160 | B3098: 17 | C3098: Plats, geofencing och fysisk kontext | D3098: 17.47 | E3098: Plats och kommunikation | F3098: FÅR INTE | G3098: Atlas FÅR INTE bygga rörelsehistorik från privata meddelanden.
... A3831: MI-19-345 | B3831: 19 | C3831: Provider-routing, kostnad, kvalitet och motståndskraft | D3831: 19.100 | E3831: Capability maturity | F3831: SKA | G3831: Pris-, policy-, kvalitet- eller incidentdrift SKA kunna sänka maturity.
A3832: MI-19-346 | B3832: 19 | C3832: Provider-routing, kostnad, kvalitet och motståndskraft | D3832: 19.100 | E3832: Capability maturity | G3832: Provider kan vara preferred för en capability och prohibited för en annan.
A3833: MI-19-347 | B3833: 19 | C3833: Provider-routing, kostnad, kvalitet och motståndskraft | D3833: 19.101 | E3833: Primära failure modes | F3833: SKA | G3833: Providerarkitekturen SKA uttryckligen skydda mot cheapest-provider bias, budget leakage, fallback bypass, retry multiplication och provider drift.
A3834: MI-19-348 | B3834: 19 | C3834: Provider-routing, kostnad, kvalitet och motståndskraft | D3834: 19.102 | E3834: Absoluta providerförbud | F3834: SKA | G3834: Listan över absoluta providerförbud SKA behandlas som canonical minimum.
A3835: MI-19-349 | B3835: 19 | C3835: Provider-routing, kostnad, kvalitet och motståndskraft | D3835: 19.102 | E3835: Absoluta providerförbud | F3835: SKA | G3835: Förbjudna beteenden SKA blockeras tekniskt där det är möjligt.
A3836: MI-20-001 | B3836: 20 | C3836: Minnesarkitektur och kunskapsgränser | D3836: 20.2 | E3836: Normativ definition av minne | F3836: SKA | G3836: Information SKA endast klassas som minne när den avsiktligt bevaras för framtida användning.
A3837: MI-20-002 | B3837: 20 | C3837: Minnesarkitektur och kunskapsgränser | D3837: 20.2 | E3837: Normativ definition av minne | F3837: FÅR INTE | G3837: Tillfällig promptkontext, cache och rå sessionhistorik FÅR INTE automatiskt betraktas som långtidsminne.
A3838: MI-20-003 | B3838: 20 | C3838: Minnesarkitektur och kunskapsgränser | D3838: 20.2 | E3838: Normativ definition av minne | F3838: SKA | G3838: Varje minnesobjekt SKA ha definierad owner, scope, klass, source, purpose och lifecycle state.
A3839: MI-20-004 | B3839: 20 | C3839: Minnesarkitektur och kunskapsgränser | D3839: 20.2 | E3839: Normativ definition av minne | F3839: SKA | G3839: Minne SKA vara åtkomstkontrollerat med samma eller striktare regler än källdatan.
A3840: MI-20-005 | B3840: 20 | C3840: Minnesarkitektur och kunskapsgränser | D3840: 20.3 | E3840: Minne kontra kontext | F3840: SKA | G3840: Minne och runtime context SKA vara separata begrepp och systemobjekt.
A3841: MI-20-006 | B3841: 20 | C3841: Minnesarkitektur och kunskapsgränser | D3841: 20.3 | E3841: Minne kontra kontext | F3841: SKA | G3841: Context builder SKA välja minsta relevanta minnesmängd.
A3842: MI-20-007 | B3842: 20 | C3842: Minnesarkitektur och kunskapsgränser | D3842: 20.3 | E3842: Minne kontra kontext | F3842: FÅR INTE | G3842: Att information används i en session FÅR INTE automatiskt skapa långtidsminne.
A3843: MI-20-008 | B3843: 20 | C3843: Minnesarkitektur och kunskapsgränser | D3843: 20.3 | E3843: Minne kontra kontext | F3843: FÅR INTE | G3843: Att information finns i långtidsminne FÅR INTE innebära att alla agents eller workflows får den i sin kontext.
A3844: MI-20-009 | B3844: 20 | C3844: Minnesarkitektur och kunskapsgränser | D3844: 20.4 | E3844: Minne kontra historik | F3844: SKA | G3844: Historik SKA skiljas från konsoliderat minne.
... A4316: MI-21-120 | B4316: 21 | C4316: Retention, radering, backup och återställningsförmåga | D4316: 21.35 | E4316: Backup kontra archive | F4316: SKA | G4316: Backup SKA optimeras för restore och integrity.
A4317: MI-21-121 | B4317: 21 | C4317: Retention, radering, backup och återställningsförmåga | D4317: 21.35 | E4317: Backup kontra archive | G4317: Samma storage kan innehålla både archive och backup endast om deras policies och identities hålls separata.
A4318: MI-21-122 | B4318: 21 | C4318: Retention, radering, backup och återställningsförmåga | D4318: 21.36 | E4318: Backup kontra snapshot | F4318: FÅR | G4318: Snapshot FÅR räknas som backupkomponent om den är isolerad, verifierad och återställningsbar.
A4319: MI-21-123 | B4319: 21 | C4319: Retention, radering, backup och återställningsförmåga | D4319: 21.36 | E4319: Backup kontra snapshot | F4319: FÅR INTE | G4319: Kortlivad lokal snapshot FÅR INTE vara enda backup mot device loss.
A4320: MI-21-124 | B4320: 21 | C4320: Retention, radering, backup och återställningsförmåga | D4320: 21.37 | E4320: Backup sets | F4320: SKA | G4320: Varje backup set SKA ha unik identity och manifest.
A4321: MI-21-125 | B4321: 21 | C4321: Retention, radering, backup och återställningsförmåga | D4321: 21.37 | E4321: Backup sets | F4321: SKA | G4321: Backup set SKA kunna kopplas till system-, schema- och policyversion.
A4322: MI-21-126 | B4322: 21 | C4322: Retention, radering, backup och återställningsförmåga | D4322: 21.37 | E4322: Backup sets | F4322: SKA | G4322: Okänd eller ofullständig manifeststatus SKA sänka backup trust.
A4323: MI-21-127 | B4323: 21 | C4323: Retention, radering, backup och återställningsförmåga | D4323: 21.38 | E4323: Full, incremental och differential backup | F4323: SKA | G4323: Backuptyp SKA vara explicit.
A4324: MI-21-128 | B4324: 21 | C4324: Retention, radering, backup och återställningsförmåga | D4324: 21.38 | E4324: Full, incremental och differential backup | F4324: SKA | G4324: Incremental restore SKA verifiera hela dependency chain.
A4325: MI-21-129 | B4325: 21 | C4325: Retention, radering, backup och återställningsförmåga | D4325: 21.38 | E4325: Full, incremental och differential backup | F4325: SKA | G4325: Saknat beroende SKA markera backupen som incomplete eller unusable.
A4326: MI-21-130 | B4326: 21 | C4326: Retention, radering, backup och återställningsförmåga | D4326: 21.38 | E4326: Full, incremental och differential backup | F4326: SKA | G4326: Backupkedja SKA testas som helhet, inte endast enskilda segment.
A4327: MI-21-131 | B4327: 21 | C4327: Retention, radering, backup och återställningsförmåga | D4327: 21.39 | E4327: Backup frequency | F4327: SKA | G4327: Backupfrekvens SKA vara definierad per dataklass eller system.
A4328: MI-21-132 | B4328: 21 | C4328: Retention, radering, backup och återställningsförmåga | D4328: 21.39 | E4328: Backup frequency | F4328: SKA | G4328: Canonical och project-critical data SKA ha backup som matchar accepterad förlustrisk.
A4329: MI-21-133 | B4329: 21 | C4329: Retention, radering, backup och återställningsförmåga | D4329: 21.39 | E4329: Backup frequency | F4329: FÅR INTE | G4329: Ephemeral och R9-data FÅR INTE säkerhetskopieras som standard.
... A5449: MI-24-164 | B5449: 24 | C5449: Kontrollytor, exekveringsytor och datalokalitet | D5449: 24.49 | E5449: Exekveringslokalitet | F5449: SKA | G5449: Task SKA kunna ha execution locality separat från data locality.
A5450: MI-24-165 | B5450: 24 | C5450: Kontrollytor, exekveringsytor och datalokalitet | D5450: 24.49 | E5450: Exekveringslokalitet | G5450: Data får vara cloud-stored men task kan ändå kräva local execution, och omvänt.
A5451: MI-24-166 | B5451: 24 | C5451: Kontrollytor, exekveringsytor och datalokalitet | D5451: 24.49 | E5451: Exekveringslokalitet | F5451: SKA | G5451: Execution locality SKA kontrolleras före job placement.
A5452: MI-24-167 | B5452: 24 | C5452: Kontrollytor, exekveringsytor och datalokalitet | D5452: 24.50 | E5452: Storagelokalitet | F5452: SKA | G5452: Storage locality SKA definiera permanent, temporary, cache och backup storage separat.
A5453: MI-24-168 | B5453: 24 | C5453: Kontrollytor, exekveringsytor och datalokalitet | D5453: 24.50 | E5453: Storagelokalitet | F5453: FÅR INTE | G5453: Temporary storage FÅR INTE ligga utanför tillåten locality.
A5454: MI-24-169 | B5454: 24 | C5454: Kontrollytor, exekveringsytor och datalokalitet | D5454: 24.50 | E5454: Storagelokalitet | F5454: FÅR INTE | G5454: Cache FÅR INTE använda bredare locality än source data.
A5455: MI-24-170 | B5455: 24 | C5455: Kontrollytor, exekveringsytor och datalokalitet | D5455: 24.50 | E5455: Storagelokalitet | F5455: SKA | G5455: Backup locality SKA uppfylla lika stark eller uttryckligt godkänd alternativ policy.
A5456: MI-24-171 | B5456: 24 | C5456: Kontrollytor, exekveringsytor och datalokalitet | D5456: 24.51 | E5456: Display locality | F5456: SKA | G5456: Känsliga data SKA ha display policy.
A5457: MI-24-172 | B5457: 24 | C5457: Kontrollytor, exekveringsytor och datalokalitet | D5457: 24.51 | E5457: Display locality | F5457: FÅR INTE | G5457: Private data FÅR INTE visas på shared eller public surface utan maskering och explicit beslut.
A5458: MI-24-173 | B5458: 24 | C5458: Kontrollytor, exekveringsytor och datalokalitet | D5458: 24.51 | E5458: Display locality | F5458: SKA | G5458: Lock-screen-display SKA använda minimerad representation.
A5459: MI-24-174 | B5459: 24 | C5459: Kontrollytor, exekveringsytor och datalokalitet | D5459: 24.51 | E5459: Display locality | F5459: SKA | G5459: Screen sharing SKA kunna begränsa eller dölja känsliga surfaces.
A5460: MI-24-175 | B5460: 24 | C5460: Kontrollytor, exekveringsytor och datalokalitet | D5460: 24.52 | E5460: Modellokalitet | F5460: SKA | G5460: Model locality SKA definiera om inferens får ske on-device, private node, Omnira cloud eller extern provider.
A5461: MI-24-176 | B5461: 24 | C5461: Kontrollytor, exekveringsytor och datalokalitet | D5461: 24.52 | E5461: Modellokalitet | F5461: FÅR INTE | G5461: Modellens availability FÅR INTE sänka localitykravet.
A5462: MI-24-177 | B5462: 24 | C5462: Kontrollytor, exekveringsytor och datalokalitet | D5462: 24.52 | E5462: Modellokalitet | F5462: FÅR INTE | G5462: Lokal modell FÅR INTE få data utanför sitt project- eller memoryscope.
... A6234: MI-26-243 | B6234: 26 | C6234: Workflowägarskap, samtidighet och dubblettskydd | D6234: 26.72 | E6234: Fan-in | F6234: SKA | G6234: Fan-in SKA definiera join condition.
A6235: MI-26-244 | B6235: 26 | C6235: Workflowägarskap, samtidighet och dubblettskydd | D6235: 26.72 | E6235: Fan-in | G6235: Join condition kan vara:
A6236: MI-26-245 | B6236: 26 | C6236: Workflowägarskap, samtidighet och dubblettskydd | D6236: 26.72 | E6236: Fan-in | F6236: FÅR INTE | G6236: First response FÅR INTE automatiskt väljas om quality- eller verificationpolicy kräver mer.
...

Sheet Per kapitel
A1: Kapitel | B1: Kapitelrubrik | C1: Antal krav | D1: Första ID | E1: Sista ID | F1: SKA | G1: FÅR INTE | H1: BÖR | I1: FÅR | J1: KAN | K1: Utan term
A2: 1 | B2: Mobile Intelligence som systemdomän i Omnira | C2: =COUNTIF('Requirement Register'!$B$2:$B$8921,A2) -> 69 | D2: MI-01-001 | E2: MI-01-069 | F2: =COUNTIFS('Requirement Register'!$B$2:$B$8921,$A2,'Requirement Register'!$F$2:$F$8921,"SKA") -> 37 | G2: =COUNTIFS('Requirement Register'!$B$2:$B$8921,$A2,'Requirement Register'!$F$2:$F$8921,"FÅR INTE") -> 31 | H2: =COUNTIFS('Requirement Register'!$B$2:$B$8921,$A2,'Requirement Register'!$F$2:$F$8921,"BÖR") -> 1 | I2: =COUNTIFS('Requirement Register'!$B$2:$B$8921,$A2,'Requirement Register'!$F$2:$F$8921,"FÅR") -> 0 | J2: =COUNTIFS('Requirement Register'!$B$2:$B$8921,$A2,'Requirement Register'!$F$2:$F$8921,"KAN") -> 0 | K2: =COUNTIFS('Requirement Register'!$B$2:$B$8921,$A2,'Requirement Register'!$F$2:$F$8921,"") -> 0
A3: 2 | B3: Vision, produktomfattning och utvecklingsväg | C3: =COUNTIF('Requirement Register'!$B$2:$B$8921,A3) -> 67 | D3: MI-02-001 | E3: MI-02-067 | F3: =COUNTIFS('Requirement Register'!$B$2:$B$8921,$A3,'Requirement Register'!$F$2:$F$8921,"SKA") -> 41 | G3: =COUNTIFS('Requirement Register'!$B$2:$B$8921,$A3,'Requirement Register'!$F$2:$F$8921,"FÅR INTE") -> 22 | H3: =COUNTIFS('Requirement Register'!$B$2:$B$8921,$A3,'Requirement Register'!$F$2:$F$8921,"BÖR") -> 2 | I3: =COUNTIFS('Requirement Register'!$B$2:$B$8921,$A3,'Requirement Register'!$F$2:$F$8921,"FÅR") -> 1 | J3: =COUNTIFS('Requirement Register'!$B$2:$B$8921,$A3,'Requirement Register'!$F$2:$F$8921,"KAN") -> 1 | K3: =COUNTIFS('Requirement Register'!$B$2:$B$8921,$A3,'Requirement Register'!$F$2:$F$8921,"") -> 0
A4: 3 | B4: Systemaktörer, roller och tillitsrelationer | C4: =COUNTIF('Requirement Register'!$B$2:$B$8921,A4) -> 115 | D4: MI-03-001 | E4: MI-03-115 | F4: =COUNTIFS('Requirement Register'!$B$2:$B$8921,$A4,'Requirement Register'!$F$2:$F$8921,"SKA") -> 70 | G4: =COUNTIFS('Requirement Register'!$B$2:$B$8921,$A4,'Requirement Register'!$F$2:$F$8921,"FÅR INTE") -> 41 | H4: =COUNTIFS('Requirement Register'!$B$2:$B$8921,$A4,'Requirement Register'!$F$2:$F$8921,"BÖR") -> 2 | I4: =COUNTIFS('Requirement Register'!$B$2:$B$8921,$A4,'Requirement Register'!$F$2:$F$8921,"FÅR") -> 1 | J4: =COUNTIFS('Requirement Register'!$B$2:$B$8921,$A4,'Requirement Register'!$F$2:$F$8921,"KAN") -> 1 | K4: =COUNTIFS('Requirement Register'!$B$2:$B$8921,$A4,'Requirement Register'!$F$2:$F$8921,"") -> 0
A5: 4 | B5: Kärnprinciper, invariants och absoluta förbud | C5: =COUNTIF('Requirement Register'!$B$2:$B$8921,A5) -> 141 | D5: MI-04-001 | E5: MI-04-141 | F5: =COUNTIFS('Requirement Register'!$B$2:$B$8921,$A5,'Requirement Register'!$F$2:$F$8921,"SKA") -> 75 | G5: =COUNTIFS('Requirement Register'!$B$2:$B$8921,$A5,'Requirement Register'!$F$2:$F$8921,"FÅR INTE") -> 59 | H5: =COUNTIFS('Requirement Register'!$B$2:$B$8921,$A5,'Requirement Register'!$F$2:$F$8921,"BÖR") -> 5 | I5: =COUNTIFS('Requirement Register'!$B$2:$B$8921,$A5,'Requirement Register'!$F$2:$F$8921,"FÅR") -> 2 | J5: =COUNTIFS('Requirement Register'!$B$2:$B$8921,$A5,'Requirement Register'!$F$2:$F$8921,"KAN") -> 0 | K5: =COUNTIFS('Requirement Register'!$B$2:$B$8921,$A5,'Requirement Register'!$F$2:$F$8921,"") -> 0
A6: 5 | B6: Authority-modellen L0–L6 | C6: =COUNTIF('Requirement Register'!$B$2:$B$8921,A6) -> 144 | D6: MI-05-001 | E6: MI-05-144 | F6: =COUNTIFS('Requirement Register'!$B$2:$B$8921,$A6,'Requirement Register'!$F$2:$F$8921,"SKA") -> 90 | G6: =COUNTIFS('Requirement Register'!$B$2:$B$8921,$A6,'Requirement Register'!$F$2:$F$8921,"FÅR INTE") -> 46 | H6: =COUNTIFS('Requirement Register'!$B$2:$B$8921,$A6,'Requirement Register'!$F$2:$F$8921,"BÖR") -> 2 | I6: =COUNTIFS('Requirement Register'!$B$2:$B$8921,$A6,'Requirement Register'!$F$2:$F$8921,"FÅR") -> 3 | J6: =COUNTIFS('Requirement Register'!$B$2:$B$8921,$A6,'Requirement Register'!$F$2:$F$8921,"KAN") -> 2 | K6: =COUNTIFS('Requirement Register'!$B$2:$B$8921,$A6,'Requirement Register'!$F$2:$F$8921,"") -> 1
A7: 6 | B7: Scope-arkitektur och capability grants | C7: =COUNTIF('Requirement Register'!$B$2:$B$8921,A7) -> 181 | D7: MI-06-001 | E7: MI-06-181 | F7: =COUNTIFS('Requirement Register'!$B$2:$B$8921,$A7,'Requirement Register'!$F$2:$F$8921,"SKA") -> 122 | G7: =COUNTIFS('Requirement Register'!$B$2:$B$8921,$A7,'Requirement Register'!$F$2:$F$8921,"FÅR INTE") -> 55 | H7: =COUNTIFS('Requirement Register'!$B$2:$B$8921,$A7,'Requirement Register'!$F$2:$F$8921,"BÖR") -> 3 | I7: =COUNTIFS('Requirement Register'!$B$2:$B$8921,$A7,'Requirement Register'!$F$2:$F$8921,"FÅR") -> 1 | J7: =COUNTIFS('Requirement Register'!$B$2:$B$8921,$A7,'Requirement Register'!$F$2:$F$8921,"KAN") -> 0 | K7: =COUNTIFS('Requirement Register'!$B$2:$B$8921,$A7,'Requirement Register'!$F$2:$F$8921,"") -> 0
A8: 7 | B8: Approval-arkitektur och mandatets livscykel | C8: =COUNTIF('Requirement Register'!$B$2:$B$8921,A8) -> 164 | D8: MI-07-001 | E8: MI-07-164 | F8: =COUNTIFS('Requirement Register'!$B$2:$B$8921,$A8,'Requirement Register'!$F$2:$F$8921,"SKA") -> 100 | G8: =COUNTIFS('Requirement Register'!$B$2:$B$8921,$A8,'Requirement Register'!$F$2:$F$8921,"FÅR INTE") -> 53 | H8: =COUNTIFS('Requirement Register'!$B$2:$B$8921,$A8,'Requirement Register'!$F$2:$F$8921,"BÖR") -> 4 | I8: =COUNTIFS('Requirement Register'!$B$2:$B$8921,$A8,'Requirement Register'!$F$2:$F$8921,"FÅR") -> 7 | J8: =COUNTIFS('Requirement Register'!$B$2:$B$8921,$A8,'Requirement Register'!$F$2:$F$8921,"KAN") -> 0 | K8: =COUNTIFS('Requirement Register'!$B$2:$B$8921,$A8,'Requirement Register'!$F$2:$F$8921,"") -> 0
A9: 8 | B9: Projektisolering, tenantgränser och Atlas globala vy | C9: =COUNTIF('Requirement Register'!$B$2:$B$8921,A9) -> 190 | D9: MI-08-001 | E9: MI-08-190 | F9: =COUNTIFS('Requirement Register'!$B$2:$B$8921,$A9,'Requirement Register'!$F$2:$F$8921,"SKA") -> 126 | G9: =COUNTIFS('Requirement Register'!$B$2:$B$8921,$A9,'Requirement Register'!$F$2:$F$8921,"FÅR INTE") -> 57 | H9: =COUNTIFS('Requirement Register'!$B$2:$B$8921,$A9,'Requirement Register'!$F$2:$F$8921,"BÖR") -> 0 | I9: =COUNTIFS('Requirement Register'!$B$2:$B$8921,$A9,'Requirement Register'!$F$2:$F$8921,"FÅR") -> 6 | J9: =COUNTIFS('Requirement Register'!$B$2:$B$8921,$A9,'Requirement Register'!$F$2:$F$8921,"KAN") -> 1 | K9: =COUNTIFS('Requirement Register'!$B$2:$B$8921,$A9,'Requirement Register'!$F$2:$F$8921,"") -> 0
A10: 9 | B10: Privacy-arkitektur och private-by-default-gränser | C10: =COUNTIF('Requirement Register'!$B$2:$B$8921,A10) -> 193 | D10: MI-09-001 | E10: MI-09-193 | F10: =COUNTIFS('Requirement Register'!$B$2:$B$8921,$A10,'Requirement Register'!$F$2:$F$8921,"SKA") -> 117 | G10: =COUNTIFS('Requirement Register'!$B$2:$B$8921,$A10,'Requirement Register'!$F$2:$F$8921,"FÅR INTE") -> 66 | H10: =COUNTIFS('Requirement Register'!$B$2:$B$8921,$A10,'Requirement Register'!$F$2:$F$8921,"BÖR") -> 5 | I10: =COUNTIFS('Requirement Register'!$B$2:$B$8921,$A10,'Requirement Register'!$F$2:$F$8921,"FÅR") -> 5 | J10: =COUNTIFS('Requirement Register'!$B$2:$B$8921,$A10,'Requirement Register'!$F$2:$F$8921,"KAN") -> 0 | K10: =COUNTIFS('Requirement Register'!$B$2:$B$8921,$A10,'Requirement Register'!$F$2:$F$8921,"") -> 0
A11: 10 | B11: Kommunikationskanaler, konton och innehållsåtkomst | C11: =COUNTIF('Requirement Register'!$B$2:$B$8921,A11) -> 213 | D11: MI-10-001 | E11: MI-10-213 | F11: =COUNTIFS('Requirement Register'!$B$2:$B$8921,$A11,'Requirement Register'!$F$2:$F$8921,"SKA") -> 138 | G11: =COUNTIFS('Requirement Register'!$B$2:$B$8921,$A11,'Requirement Register'!$F$2:$F$8921,"FÅR INTE") -> 65 | H11: =COUNTIFS('Requirement Register'!$B$2:$B$8921,$A11,'Requirement Register'!$F$2:$F$8921,"BÖR") -> 6 | I11: =COUNTIFS('Requirement Register'!$B$2:$B$8921,$A11,'Requirement Register'!$F$2:$F$8921,"FÅR") -> 4 | J11: =COUNTIFS('Requirement Register'!$B$2:$B$8921,$A11,'Requirement Register'!$F$2:$F$8921,"KAN") -> 0 | K11: =COUNTIFS('Requirement Register'!$B$2:$B$8921,$A11,'Requirement Register'!$F$2:$F$8921,"") -> 0
A12: 11 | B12: Utgående kommunikation, varumärkesidentitet och mänsklig representation | C12: =COUNTIF('Requirement Register'!$B$2:$B$8921,A12) -> 221 | D12: MI-11-001 | E12: MI-11-221 | F12: =COUNTIFS('Requirement Register'!$B$2:$B$8921,$A12,'Requirement Register'!$F$2:$F$8921,"SKA") -> 138 | G12: =COUNTIFS('Requirement Register'!$B$2:$B$8921,$A12,'Requirement Register'!$F$2:$F$8921,"FÅR INTE") -> 71 | H12: =COUNTIFS('Requirement Register'!$B$2:$B$8921,$A12,'Requirement Register'!$F$2:$F$8921,"BÖR") -> 7 | I12: =COUNTIFS('Requirement Register'!$B$2:$B$8921,$A12,'Requirement Register'!$F$2:$F$8921,"FÅR") -> 5 | J12: =COUNTIFS('Requirement Register'!$B$2:$B$8921,$A12,'Requirement Register'!$F$2:$F$8921,"KAN") -> 0 | K12: =COUNTIFS('Requirement Register'!$B$2:$B$8921,$A12,'Requirement Register'!$F$2:$F$8921,"") -> 0
A13: 12 | B13: Notifieringar, mänsklig uppmärksamhet och prioritetsgovernance | C13: =COUNTIF('Requirement Register'!$B$2:$B$8921,A13) -> 225 | D13: MI-12-001 | E13: MI-12-225 | F13: =COUNTIFS('Requirement Register'!$B$2:$B$8921,$A13,'Requirement Register'!$F$2:$F$8921,"SKA") -> 146 | G13: =COUNTIFS('Requirement Register'!$B$2:$B$8921,$A13,'Requirement Register'!$F$2:$F$8921,"FÅR INTE") -> 58 | H13: =COUNTIFS('Requirement Register'!$B$2:$B$8921,$A13,'Requirement Register'!$F$2:$F$8921,"BÖR") -> 8 | I13: =COUNTIFS('Requirement Register'!$B$2:$B$8921,$A13,'Requirement Register'!$F$2:$F$8921,"FÅR") -> 13 | J13: =COUNTIFS('Requirement Register'!$B$2:$B$8921,$A13,'Requirement Register'!$F$2:$F$8921,"KAN") -> 0 | K13: =COUNTIFS('Requirement Register'!$B$2:$B$8921,$A13,'Requirement Register'!$F$2:$F$8921,"") -> 0
... A33: 32 | B33: Mobilupplevelse, daglig drift och canonical implementation contract | C33: =COUNTIF('Requirement Register'!$B$2:$B$8921,A33) -> 350 | D33: MI-32-001 | E33: MI-32-350 | F33: =COUNTIFS('Requirement Register'!$B$2:$B$8921,$A33,'Requirement Register'!$F$2:$F$8921,"SKA") -> 253 | G33: =COUNTIFS('Requirement Register'!$B$2:$B$8921,$A33,'Requirement Register'!$F$2:$F$8921,"FÅR INTE") -> 91 | H33: =COUNTIFS('Requirement Register'!$B$2:$B$8921,$A33,'Requirement Register'!$F$2:$F$8921,"BÖR") -> 2 | I33: =COUNTIFS('Requirement Register'!$B$2:$B$8921,$A33,'Requirement Register'!$F$2:$F$8921,"FÅR") -> 4 | J33: =COUNTIFS('Requirement Register'!$B$2:$B$8921,$A33,'Requirement Register'!$F$2:$F$8921,"KAN") -> 0 | K33: =COUNTIFS('Requirement Register'!$B$2:$B$8921,$A33,'Requirement Register'!$F$2:$F$8921,"") -> 0
B34: Totalt | C34: =SUM(C2:C33) -> 8920 | F34: =SUM(F2:F33) -> 5886 | G34: =SUM(G2:G33) -> 2602 | H34: =SUM(H2:H33) -> 210 | I34: =SUM(I2:I33) -> 207 | J34: =SUM(J2:J33) -> 6 | K34: =SUM(K2:K33) -> 9

Sheet Läsanvisning
A1: Omnira — Mobile Intelligence & Device Control — Requirement Register
A2: Status | B2: Canonical Edition v1.0 — APPROVED
A4: Utgåva | B4: r2 — efter normativ terminologistandardisering
A5: Innehåll | B5: Samtliga 8 920 normativa kontrakt ur Kapitel 1–32.
A6: Källa | B6: Sources/Canonical-Source-Set-v1.0/ — canonical source-set med 22 tillämpade terminologikorrigeringar.
A7: Ändring mot r1 | B7: 22 krav standardiserade till FÅR INTE. Ingen annan textändring. FÅR INTE: 2 580 → 2 602. SKA INTE: 2 → 0. ÄR FÖRBJUDEN/-ET/-NA: 20 → 0.
A8: Extraktionsmetod | B8: Fristående stycke som exakt matchar MI-KK-NNN är ett kontrakt-ID. Kravtexten är omedelbart följande stycke, ordagrant.
A9: Normativ term | B9: Första term ur Chapter Plan §7-vokabulären, prioritet FÅR INTE, SKA INTE, SKA, FÅR, BÖR, KAN.
A10: Utan term | B10: 9 krav (var 29) saknar §7-term. Samtliga är beskrivande eller uppräknande satser där normativ term inte är avsedd.
A11: Verifiering | B11: 8 920 ID, inga dubbletter, inga luckor, samtliga har kravtext, noll kvarvarande SKA INTE eller ÄR FÖRBJUDEN.
A13: Godkännandestatus | B13: APPROVED
A14: Godkänd av | B14: André Hultgren
A15: Godkännandedatum | B15: 2026-07-30
... A17: Ändring mot r2 | B17: Endast status- och paketmetadata. Ingen kravtext, inget ID och ingen tolkning har ändrats.
